cinefiles/.DS_Store
cinefiles/HISTORY.md
cinefiles/IMDBPageParser.py
cinefiles/__init__.py
cinefiles/__main__.py
cinefiles/cinefiles.py
cinefiles/cinefolders.py
cinefiles/googlesearch.py
cinefiles/search.py
cinefiles/templatex.py
cinefiles/title.py
cinefiles/ydlhandlers.py
cinefiles/resources/.DS_Store
cinefiles/resources/flarevideo.css
cinefiles/resources/flarevideo.default.css
cinefiles/resources/flarevideo.js
cinefiles/resources/flarevideo.vimeo.css
cinefiles/resources/index.html
cinefiles/resources/jquery-1.4.2.js
cinefiles/resources/jquery-3.1.1.min.js
cinefiles/resources/jquery.flash.js
cinefiles/resources/jquery.tablesorter.min.js
cinefiles/resources/jquery.ui.slider.js
cinefiles/resources/main.css
cinefiles/resources/masterindex.html
cinefiles/resources/script-insert.html
cinefiles/resources/youtube-dl_config
cinefiles/resources/images/.DS_Store
cinefiles/resources/images/asc.png
cinefiles/resources/images/bg.png
cinefiles/resources/images/desc.png
cinefiles/resources/images/tablebg.png
cinefiles/resources/images/tmdb-attribution-rectangle.png
cinefiles/resources/images/default/full-screen.png
cinefiles/resources/images/default/pause.png
cinefiles/resources/images/default/play.png
cinefiles/resources/images/default/slider-thumb.png
cinefiles/resources/images/default/vol-max.png
cinefiles/resources/images/default/vol-min.png
cinefiles/resources/images/default/volume-thumb.png
cinefiles/resources/images/vimeo/full-screen.png
cinefiles/resources/images/vimeo/pause.png
cinefiles/resources/images/vimeo/play.png
cinefiles/tmdb/__init__.py
cinefiles/tmdb/exceptions.py
cinefiles/tmdb/movie.py
cinefiles/tmdb/tmdb.py
cinefiles-1.1.1.dist-info/DESCRIPTION.rst
cinefiles-1.1.1.dist-info/METADATA
cinefiles-1.1.1.dist-info/RECORD
cinefiles-1.1.1.dist-info/WHEEL
cinefiles-1.1.1.dist-info/metadata.json
cinefiles-1.1.1.dist-info/top_level.txt
