Metadata-Version: 2.0
Name: cinefiles
Version: 1.1.1
Summary: Organize your movie folder and files
Home-page: https://github.com/hgibs/cinefiles
Author: Holland Gibson
Author-email: cinefiles-hgibs@googlegroups.com
License: Apache 2.0
Keywords: movies organization folder
Platform: UNKNOWN
Classifier: Development Status :: 5 - Production/Stable
Classifier: Intended Audience :: End Users/Desktop
Classifier: Topic :: Desktop Environment :: File Managers
Classifier: Topic :: Games/Entertainment
Classifier: License :: OSI Approved :: Apache Software License
Classifier: Programming Language :: Python :: 3
Classifier: Programming Language :: Python :: 3.4
Classifier: Programming Language :: Python :: 3.5
Classifier: Programming Language :: Python :: 3.6
Requires-Dist: google-api-python-client (<2,>=1.6.2)
Requires-Dist: guessit (>=2.1.1,<3)
Requires-Dist: lxml (>=3.7.3,<4)
Requires-Dist: pycountry (>=17.0.0,<18)
Requires-Dist: requests (>=2.4.3,<3)
Requires-Dist: youtube-dl (>=2017.2.17)
Provides-Extra: dev
Requires-Dist: twine; extra == 'dev'
Requires-Dist: wheel; extra == 'dev'
Provides-Extra: test
Requires-Dist: codecov; extra == 'test'
Requires-Dist: pytest; extra == 'test'
Requires-Dist: pytest-console-scripts; extra == 'test'
Requires-Dist: pytest-cov; extra == 'test'
Requires-Dist: pytest-pep8; extra == 'test'
